{
    "login": "mathkruger",
    "id": 20642635,
    "node_id": "MDQ6VXNlcjIwNjQyNjM1",
    "avatar_url": "https://avatars.githubusercontent.com/u/20642635?v=4",
    "gravatar_id": "",
    "url": "https://api.github.com/users/mathkruger",
    "html_url": "https://github.com/mathkruger",
    "followers_url": "https://api.github.com/users/mathkruger/followers",
    "following_url": "https://api.github.com/users/mathkruger/following{/other_user}",
    "gists_url": "https://api.github.com/users/mathkruger/gists{/gist_id}",
    "starred_url": "https://api.github.com/users/mathkruger/starred{/owner}{/repo}",
    "subscriptions_url": "https://api.github.com/users/mathkruger/subscriptions",
    "organizations_url": "https://api.github.com/users/mathkruger/orgs",
    "repos_url": "https://api.github.com/users/mathkruger/repos",
    "events_url": "https://api.github.com/users/mathkruger/events{/privacy}",
    "received_events_url": "https://api.github.com/users/mathkruger/received_events",
    "type": "User",
    "site_admin": false,
    "name": "Matheus S. Kruger",
    "company": "CI&T",
    "blog": "facebook.com/mathkruger",
    "location": "SP - Brazil",
    "email": null,
    "hireable": null,
    "bio": "FullStack Web Developer\r\n",
    "twitter_username": "_mathkruger",
    "public_repos": 71,
    "public_gists": 10,
    "followers": 34,
    "following": 86,
    "created_at": "2016-07-25T13:07:10Z",
    "updated_at": "2022-10-09T17:35:36Z"
}